namer/__init__.py
namer/__main__.py
namer/data/__init__.py
namer/data/adjectives.py
namer/data/animals.py
namer/data/architecture.py
namer/data/art.py
namer/data/astronomy.py
namer/data/biology.py
namer/data/chemistry.py
namer/data/computer_science.py
namer/data/countries.py
namer/data/economy.py
namer/data/food.py
namer/data/general.py
namer/data/geography.py
namer/data/history.py
namer/data/literature.py
namer/data/math.py
namer/data/medicine.py
namer/data/microbiology.py
namer/data/molecular_biology.py
namer/data/music.py
namer/data/physics.py
namer/data/plants.py
namer/data/scientists.py
namer/data/sports.py
namer/data/technology.py
unique_namer-1.6.2.dist-info/licenses/LICENSE
unique_namer-1.6.2.dist-info/METADATA
unique_namer-1.6.2.dist-info/WHEEL
unique_namer-1.6.2.dist-info/entry_points.txt
unique_namer-1.6.2.dist-info/top_level.txt
unique_namer-1.6.2.dist-info/RECORD
