Metadata-Version: 2.4
Name: unique-namer
Version: 1.6.2
Summary: Generate unique, human-readable, and memorable names or identifiers
Author-email: Andrzej Zielezinski <a.zielezinski@gmail.com>
License: MIT License
Project-URL: Homepage, https://github.com/aziele/unique-namer
Keywords: random,unique,name,id,generate,namer
Classifier: License :: OSI Approved :: MIT License
Classifier: Programming Language :: Python
Classifier: Programming Language :: Python :: 3
Classifier: Operating System :: OS Independent
Classifier: Natural Language :: English
Classifier: Intended Audience :: Developers
Classifier: Intended Audience :: Science/Research
Classifier: Topic :: Software Development :: Libraries
Classifier: Topic :: Software Development :: Libraries :: Python Modules
Requires-Python: >=3.6
License-File: LICENSE
Dynamic: license-file
